accml/__init__.py
accml-0.0.0.dist-info/LICENSE
accml-0.0.0.dist-info/METADATA
accml-0.0.0.dist-info/WHEEL
accml-0.0.0.dist-info/RECORD
